<?xml version="1.0" ?><annotation>
	<folder>JPEGImages</folder>
	<filename>200208.jpg</filename>
	<path>JPEGImages/200208.jpg</path>
	<source>
		<database>Unknown</database>
	</source>
	<size>
		<width>284</width>
		<height>202</height>
		<depth>3</depth>
	</size>
	<segmented>0</segmented>
	<object>
		<name>smoke</name>
		<pose>Unspecified</pose>
		<truncated>0</truncated>
		<difficult>0</difficult>
		<bndbox>
			<xmin>68</xmin>
			<ymin>46</ymin>
			<xmax>200</xmax>
			<ymax>83</ymax>
		</bndbox>
	</object>
</annotation>